distributed_lock/__init__.py
distributed_lock/distributed_lock.py
distributed_lock-1.0.dist-info/LICENSE
distributed_lock-1.0.dist-info/METADATA
distributed_lock-1.0.dist-info/WHEEL
distributed_lock-1.0.dist-info/top_level.txt
distributed_lock-1.0.dist-info/RECORD
